gym_chess/__init__.py
gym_chess/alphazero/__init__.py
gym_chess/alphazero/board_encoding.py
gym_chess/alphazero/move_encoding/__init__.py
gym_chess/alphazero/move_encoding/knightmoves.py
gym_chess/alphazero/move_encoding/queenmoves.py
gym_chess/alphazero/move_encoding/underpromotions.py
gym_chess/alphazero/move_encoding/utils.py
gym_chess/envs.py
gym_chess-0.1.0.dist-info/LICENSE.md
gym_chess-0.1.0.dist-info/WHEEL
gym_chess-0.1.0.dist-info/METADATA
gym_chess-0.1.0.dist-info/RECORD
