Metadata-Version: 2.1
Name: gym-chess
Version: 0.1.0
Summary: OpenAI Gym environments for Chess
Home-page: https://github.com/iamlucaswolf/gym-chess
License: GPL-3.0-or-later
Author: Lucas Wolf
Author-email: iamlucaswolf@gmail.com
Requires-Python: >=3.6,<4.0
Classifier: License :: OSI Approved :: GNU General Public License v3 or later (GPLv3+)
Classifier: Programming Language :: Python :: 3
Classifier: Programming Language :: Python :: 3.6
Classifier: Programming Language :: Python :: 3.7
Classifier: Programming Language :: Python :: 3.8
Requires-Dist: gym (>=0.17.2,<0.18.0)
Requires-Dist: python-chess (>=0.31.1,<0.32.0)
Project-URL: Repository, https://github.com/iamlucaswolf/gym-chess
